codebreaking_at_cal/__init__.py
codebreaking_at_cal/caesar.py
codebreaking_at_cal/common_words.csv
codebreaking_at_cal/utils.py
codebreaking_at_cal/vignere.py
codebreaking_at_cal-0.0.10.dist-info/METADATA
codebreaking_at_cal-0.0.10.dist-info/WHEEL
codebreaking_at_cal-0.0.10.dist-info/top_level.txt
codebreaking_at_cal-0.0.10.dist-info/RECORD
