Metadata-Version: 2.1
Name: codebreaking-at-cal
Version: 0.0.10
Summary: CBC package
Home-page: https://github.com/CodebreakingAtCal/codebreaking-package
Author: Ryan Cottone
Author-email: rcottone@nvidia.com
Requires-Dist: requests
